zsingleton/__init__.py
zsingleton/singleton_base.py
zsingleton/singleton_decorator.py
zsingleton/singleton_metaclass.py
zsingleton-1.0.0.dist-info/METADATA
zsingleton-1.0.0.dist-info/RECORD
zsingleton-1.0.0.dist-info/WHEEL
zsingleton-1.0.0.dist-info/top_level.txt
